README.rst
microsecrets.py
setup.py
/home/andy/gov/microsecrets/bin/microsecrets-upload
/home/andy/gov/microsecrets/bin/microsecrets-with-env
bin/microsecrets-download
bin/microsecrets-upload
bin/microsecrets-with-env
microsecrets.egg-info/PKG-INFO
microsecrets.egg-info/SOURCES.txt
microsecrets.egg-info/dependency_links.txt
microsecrets.egg-info/requires.txt
microsecrets.egg-info/top_level.txt