Metadata-Version: 1.1
Name: microsecrets
Version: 0.3.4
Summary: Simple secrets management powered by Amazon S3 + KMS
Home-page: https://github.com/uscis/microsecrets
Author: Andy Brody
Author-email: git@abrody.com
License: Public Domain
Platform: UNKNOWN
Classifier: Development Status :: 3 - Alpha
Classifier: Intended Audience :: Developers
Classifier: Intended Audience :: System Administrators
Classifier: Topic :: Security
Classifier: License :: Public Domain
Classifier: Programming Language :: Python :: 2
Classifier: Programming Language :: Python :: 2.6
Classifier: Programming Language :: Python :: 2.7
